python_rekor_monitor/__init__.py
python_rekor_monitor/main.py
python_rekor_monitor/merkle_proof.py
python_rekor_monitor/util.py
python_rekor_monitor-0.1.1.dist-info/METADATA
python_rekor_monitor-0.1.1.dist-info/WHEEL
python_rekor_monitor-0.1.1.dist-info/entry_points.txt
python_rekor_monitor-0.1.1.dist-info/RECORD
