Metadata-Version: 2.1
Name: python-rekor-monitor
Version: 0.1.1
Summary: Based on Rekor-Monitor
License: MIT
Author: mayank-ramnani
Author-email: mayankr99@gmail.com
Requires-Python: >=3.12,<4.0
Classifier: License :: OSI Approved :: MIT License
Classifier: Programming Language :: Python :: 3
Classifier: Programming Language :: Python :: 3.12
Requires-Dist: cryptography (>=43.0,<44.0)
Requires-Dist: pytest (>=8.3.3,<9.0.0)
Requires-Dist: requests (>=2.32,<3.0)
Requires-Dist: ruff (>=0.6.9,<0.7.0)
